hb/cli.py
hb/main.py
hb-1.4.2.dist-info/entry_points.txt
hb-1.4.2.dist-info/LICENSE
hb-1.4.2.dist-info/WHEEL
hb-1.4.2.dist-info/METADATA
hb-1.4.2.dist-info/RECORD
